[
  {
    "id": "sDCJIPtXY",
    "username": "Jasmin",
    "price": 12,
    "createdAt": "2023-05-13T10:02:02.679Z",
    "updatedAt": "2023-05-13T10:02:02.679Z"
  },
  {
    "id": "6k1dvK0rQ",
    "username": "jasmin akter",
    "price": 12,
    "createdAt": "2023-05-13T10:02:17.127Z",
    "updatedAt": "2023-05-13T10:02:57.708Z"
  },
  {
    "id": "3qmWW3QMB0",
    "username": "jasmin akter",
    "price": 12,
    "createdAt": "2023-05-13T10:02:17.127Z",
    "updatedAt": "2023-05-13T10:02:57.708Z"
  },
  {
    "id": "C3_ScdeYRg",
    "username": "jasmin akter",
    "price": 12,
    "createdAt": "2023-05-13T10:02:17.127Z",
    "updatedAt": "2023-05-13T10:02:57.708Z"
  },
  {
    "id": "_L8eUEWJwt",
    "username": "jasmin akter",
    "price": 12,
    "createdAt": "2023-05-13T10:02:17.127Z",
    "updatedAt": "2023-05-13T10:02:57.708Z"
  },
  {
    "id": "l5o5jofPHb",
    "username": "jasmin akter",
    "price": 12,
    "createdAt": "2023-05-13T10:02:17.127Z",
    "updatedAt": "2023-05-13T10:02:57.709Z"
  }
]
